{
  "logs": [
    {
      "id": 1,
      "message": "Changed hard drive on workstation 005",
      "attention": false,
      "date": "03-02-2021",
      "tech": "Sam Gamgee"
    },
    {
      "id": 2,
      "message": "Workstation 007 not posting",
      "attention": true,
      "date": "03-02-2020",
      "tech": "John Doe"
    },
    {
      "id": 3,
      "message": "Changed mermory on workstation 050",
      "attention": false,
      "date": "03-22-2021",
      "tech": "Sara Wilson"
    }
  ],
  "techs": [
    {
      "id": 1,
      "firstName": "John",
      "lastName": "Doe"
    },
    {
      "id": 2,
      "firstName": "Sam",
      "lastName": "Gamgee"
    },
    {
      "id": 3,
      "firstName": "Sara",
      "lastName": "Wilson"
    },
    {
      "firstName": "Jen",
      "lastName": "Williams",
      "id": 4
    }
  ]
}